data_processing/data_access/__init__.py
data_processing/data_access/arrow_s3.py
data_processing/data_access/compute_test_data_location.py
data_processing/data_access/data_access.py
data_processing/data_access/data_access_factory.py
data_processing/data_access/data_access_hf.py
data_processing/data_access/data_access_local.py
data_processing/data_access/data_access_s3.py
data_processing/examples/noop/python/__init__.py
data_processing/examples/noop/python/noop1_transform.py
data_processing/examples/noop/python/noop_folder_transform.py
data_processing/examples/noop/python/noop_local.py
data_processing/examples/noop/python/noop_local_python.py
data_processing/examples/noop/python/noop_local_python_multiprocessor.py
data_processing/examples/noop/python/noop_transform.py
data_processing/examples/noop/ray/__init__.py
data_processing/examples/noop/ray/noop_folder_transform.py
data_processing/examples/noop/ray/noop_local_ray.py
data_processing/examples/noop/ray/noop_transform.py
data_processing/examples/pipeline/python/__init__.py
data_processing/examples/pipeline/python/pipeline_local_python.py
data_processing/examples/pipeline/python/pipeline_local_python_fork.py
data_processing/examples/pipeline/python/pipeline_transform.py
data_processing/examples/pipeline/python/pipeline_transform_fork.py
data_processing/examples/pipeline/ray/__init__.py
data_processing/examples/pipeline/ray/pipeline_local_ray.py
data_processing/examples/pipeline/ray/pipeline_transform.py
data_processing/examples/resize/python/__init__.py
data_processing/examples/resize/python/resize_local.py
data_processing/examples/resize/python/resize_local_python.py
data_processing/examples/resize/python/resize_transform.py
data_processing/examples/resize/ray/__init__.py
data_processing/examples/resize/ray/resize_local_ray.py
data_processing/examples/resize/ray/resize_transform.py
data_processing/runtime/__init__.py
data_processing/runtime/execution_configuration.py
sdpk-0.0.2.dist-info/METADATA
sdpk-0.0.2.dist-info/WHEEL
sdpk-0.0.2.dist-info/top_level.txt
sdpk-0.0.2.dist-info/RECORD
